<?xml version="1.0" encoding="UTF-8"?>
<PathOfBuilding>
	<Build level="100" targetVersion="3_0" banditNormal="None" bandit="None" banditMerciless="None" className="Witch" ascendClassName="Occultist" mainSocketGroup="6" viewMode="CALCS" banditCruel="None">
		<PlayerStat stat="AverageDamage" value="100414.0557"/>
		<PlayerStat stat="Speed" value="4.148"/>
		<PlayerStat stat="Speed" value="4.148"/>
		<PlayerStat stat="PreEffectiveCritChance" value="6.54"/>
		<PlayerStat stat="CritChance" value="6.213"/>
		<PlayerStat stat="CritMultiplier" value="1"/>
		<PlayerStat stat="HitChance" value="95"/>
		<PlayerStat stat="TotalDPS" value="416517.5030436"/>
		<PlayerStat stat="TotalDot" value="0"/>
		<PlayerStat stat="WithPoisonDPS" value="416517.5030436"/>
		<PlayerStat stat="ManaCost" value="25"/>
		<PlayerStat stat="Str" value="293"/>
		<PlayerStat stat="ReqStr" value="159"/>
		<PlayerStat stat="Dex" value="155"/>
		<PlayerStat stat="ReqDex" value="155"/>
		<PlayerStat stat="Int" value="1792"/>
		<PlayerStat stat="ReqInt" value="194"/>
		<PlayerStat stat="Life" value="1"/>
		<PlayerStat stat="Spec:LifeInc" value="0"/>
		<PlayerStat stat="LifeUnreserved" value="1"/>
		<PlayerStat stat="LifeUnreservedPercent" value="100"/>
		<PlayerStat stat="LifeRegen" value="0"/>
		<PlayerStat stat="LifeLeechGainRate" value="0"/>
		<PlayerStat stat="Mana" value="3038"/>
		<PlayerStat stat="Spec:ManaInc" value="67"/>
		<PlayerStat stat="ManaUnreserved" value="822"/>
		<PlayerStat stat="ManaUnreservedPercent" value="27.057274522712"/>
		<PlayerStat stat="ManaRegen" value="102.3"/>
		<PlayerStat stat="ManaLeechGainRate" value="0"/>
		<PlayerStat stat="TotalDegen" value="625.856"/>
		<PlayerStat stat="NetLifeRegen" value="4707.844"/>
		<PlayerStat stat="EnergyShield" value="17779"/>
		<PlayerStat stat="Spec:EnergyShieldInc" value="139"/>
		<PlayerStat stat="EnergyShieldRegen" value="5333.7"/>
		<PlayerStat stat="EnergyShieldLeechGainRate" value="3555.8"/>
		<PlayerStat stat="Evasion" value="23201"/>
		<PlayerStat stat="Spec:EvasionInc" value="24"/>
		<PlayerStat stat="MeleeEvadeChance" value="63"/>
		<PlayerStat stat="MeleeEvadeChance" value="63"/>
		<PlayerStat stat="ProjectileEvadeChance" value="63"/>
		<PlayerStat stat="Armour" value="396"/>
		<PlayerStat stat="Spec:ArmourInc" value="52"/>
		<PlayerStat stat="PhysicalDamageReduction" value="15"/>
		<PlayerStat stat="EffectiveMovementSpeedMod" value="2.22"/>
		<PlayerStat stat="BlockChance" value="25"/>
		<PlayerStat stat="SpellBlockChance" value="0"/>
		<PlayerStat stat="AttackDodgeChance" value="0"/>
		<PlayerStat stat="SpellDodgeChance" value="0"/>
		<PlayerStat stat="FireResist" value="75"/>
		<PlayerStat stat="ColdResist" value="75"/>
		<PlayerStat stat="LightningResist" value="75"/>
		<PlayerStat stat="ChaosResist" value="100"/>
		<PlayerStat stat="FireResistOverCap" value="59"/>
		<PlayerStat stat="ColdResistOverCap" value="9"/>
		<PlayerStat stat="LightningResistOverCap" value="59"/>
		<PlayerStat stat="ChaosResistOverCap" value="0"/>
		<PlayerStat stat="PowerCharges" value="0"/>
		<PlayerStat stat="PowerChargesMax" value="3"/>
		<PlayerStat stat="FrenzyCharges" value="0"/>
		<PlayerStat stat="FrenzyChargesMax" value="3"/>
		<PlayerStat stat="EnduranceCharges" value="3"/>
		<PlayerStat stat="EnduranceChargesMax" value="3"/>
	</Build>
	<Import/>
	<Calcs>
		<Input name="misc_buffMode" string="EFFECTIVE"/>
		<Input name="skill_number" number="6"/>
		<Section collapsed="false" id="SkillSelect"/>
		<Section collapsed="false" id="HitDamage"/>
		<Section collapsed="false" id="Dot"/>
		<Section collapsed="false" id="Speed"/>
		<Section collapsed="false" id="Crit"/>
		<Section collapsed="false" id="HitChance"/>
		<Section collapsed="false" id="SkillTypeStats"/>
		<Section collapsed="false" id="Bleed"/>
		<Section collapsed="false" id="Poison"/>
		<Section collapsed="false" id="Ignite"/>
		<Section collapsed="false" id="Decay"/>
		<Section collapsed="false" id="LeechGain"/>
		<Section collapsed="false" id="MiscEffects"/>
		<Section collapsed="false" id="Attributes"/>
		<Section collapsed="false" id="Life"/>
		<Section collapsed="false" id="Mana"/>
		<Section collapsed="false" id="EnergyShield"/>
		<Section collapsed="false" id="Armour"/>
		<Section collapsed="false" id="Evasion"/>
		<Section collapsed="false" id="Resist"/>
		<Section collapsed="false" id="DamageTaken"/>
		<Section collapsed="false" id="MiscDefences"/>
	</Calcs>
	<Skills defaultGemQuality="nil" defaultGemLevel="nil" sortGemsByDPS="true">
		<Skill mainActiveSkillCalcs="1" enabled="true" slot="Boots" mainActiveSkill="1">
			<Gem level="20" enableGlobal1="true" gemId="Metadata/Items/Gems/SupportGemBlasphemy" enableGlobal2="false" quality="23" skillId="SupportBlasphemy" enabled="true" nameSpec="Blasphemy"/>
			<Gem level="4" enableGlobal1="true" gemId="Metadata/Items/Gems/SupportGemAdditionalXP" enableGlobal2="false" quality="20" skillId="SupportAdditionalXP" enabled="true" nameSpec="Enlighten"/>
			<Gem level="21" enableGlobal1="true" gemId="Metadata/Items/Gems/SkillGemEnfeeble" enableGlobal2="false" quality="20" skillId="Enfeeble" enabled="true" nameSpec="Enfeeble"/>
			<Gem level="20" enableGlobal1="true" gemId="Metadata/Items/Gems/SkillGemProjectileWeakness" enableGlobal2="false" quality="20" skillId="ProjectileWeakness" enabled="true" nameSpec="Projectile Weakness"/>
		</Skill>
		<Skill mainActiveSkillCalcs="1" enabled="true" slot="Weapon 2" mainActiveSkill="1">
			<Gem level="1" enableGlobal1="true" gemId="Metadata/Items/Gems/SkillGemClarity" enableGlobal2="false" quality="0" skillId="Clarity" enabled="true" nameSpec="Clarity"/>
			<Gem level="1" enableGlobal1="true" gemId="Metadata/Items/Gems/SkillGemPortal" enableGlobal2="false" quality="0" skillId="Portal" enabled="true" nameSpec="Portal"/>
			<Gem level="20" enableGlobal1="true" gemId="Metadata/Items/Gems/SkillGemBloodRage" enableGlobal2="false" quality="20" skillId="BloodRage" enabled="true" nameSpec="Blood Rage"/>
		</Skill>
		<Skill mainActiveSkillCalcs="1" enabled="true" slot="Weapon 1" mainActiveSkill="1">
			<Gem level="1" enableGlobal1="true" gemId="Metadata/Items/Gems/SupportGemFortify" enableGlobal2="false" quality="15" skillId="SupportFortify" enabled="true" nameSpec="Fortify"/>
			<Gem level="20" enableGlobal1="true" gemId="Metadata/Items/Gems/SkillGemWhirlingBlades" enableGlobal2="false" quality="17" skillId="WhirlingBlades" enabled="true" nameSpec="Whirling Blades"/>
			<Gem level="20" enableGlobal1="true" gemId="Metadata/Items/Gems/SupportGemFasterAttack" enableGlobal2="false" quality="20" skillId="SupportFasterAttack" enabled="true" nameSpec="Faster Attacks"/>
		</Skill>
		<Skill mainActiveSkillCalcs="1" enabled="true" slot="Helmet" mainActiveSkill="1">
			<Gem level="21" enableGlobal1="true" gemId="Metadata/Items/Gems/SkillGemConductivity" enableGlobal2="false" quality="20" skillId="Conductivity" enabled="true" nameSpec="Conductivity"/>
			<Gem level="20" enableGlobal1="false" gemId="Metadata/Items/Gems/SkillGemVaalDiscipline" enableGlobal2="false" quality="0" skillId="VaalDiscipline" enabled="true" nameSpec="Vaal Discipline"/>
			<Gem level="4" enableGlobal1="true" gemId="Metadata/Items/Gems/SupportGemAdditionalXP" enableGlobal2="false" quality="20" skillId="SupportAdditionalXP" enabled="true" nameSpec="Enlighten"/>
			<Gem level="20" enableGlobal1="true" gemId="Metadata/Items/Gems/SupportGemBlasphemy" enableGlobal2="false" quality="20" skillId="SupportBlasphemy" enabled="true" nameSpec="Blasphemy"/>
		</Skill>
		<Skill mainActiveSkillCalcs="1" enabled="true" slot="Gloves" mainActiveSkill="1">
			<Gem level="20" enableGlobal1="false" gemId="Metadata/Items/Gems/SkillGemVaalGrace" enableGlobal2="false" quality="0" skillId="VaalGrace" enabled="true" nameSpec="Vaal Grace"/>
			<Gem level="20" enableGlobal1="true" gemId="Metadata/Items/Gems/SupportGemIncreasedDuration" enableGlobal2="false" quality="20" skillId="SupportIncreasedDuration" enabled="true" nameSpec="Increased Duration"/>
			<Gem level="20" enableGlobal1="true" gemId="Metadata/Items/Gems/SkillGemImmortalCall" enableGlobal2="false" quality="0" skillId="ImmortalCall" enabled="true" nameSpec="Immortal Call"/>
			<Gem level="20" enableGlobal1="true" gemId="Metadata/Items/Gems/SupportGemCastOnDamageTaken" enableGlobal2="false" quality="0" skillId="SupportCastOnDamageTaken" enabled="true" nameSpec="Cast when Damage Taken"/>
		</Skill>
		<Skill mainActiveSkillCalcs="1" enabled="true" slot="Body Armour" mainActiveSkill="1">
			<Gem level="21" enableGlobal1="true" gemId="Metadata/Items/Gems/SupportGemWeaponElementalDamage" enableGlobal2="false" quality="20" skillId="SupportWeaponElementalDamage" enabled="true" nameSpec="Elemental Damage with Attacks"/>
			<Gem level="21" enableGlobal1="true" gemId="Metadata/Items/Gems/SkillGemMoltenStrike" enableGlobal2="false" quality="0" skillPart="2" skillId="MoltenStrike" skillPartCalcs="2" enabled="true" nameSpec="Molten Strike"/>
			<Gem level="21" enableGlobal1="true" gemId="Metadata/Items/Gems/SupportGemMeleeDamageOnFullLife" enableGlobal2="false" quality="20" skillId="SupportMeleeDamageOnFullLife" enabled="true" nameSpec="Damage on Full Life"/>
			<Gem level="21" enableGlobal1="true" gemId="Metadata/Items/Gems/SupportGemElementalFocus" enableGlobal2="false" quality="20" skillId="SupportElementalFocus" enabled="true" nameSpec="Elemental Focus"/>
			<Gem level="21" enableGlobal1="true" gemId="Metadata/Items/Gems/SupportGemSpiritStrike" enableGlobal2="false" quality="20" skillId="SupportSpiritStrike" enabled="true" nameSpec="Ancestral Call"/>
			<Gem level="21" enableGlobal1="true" gemId="Metadata/Items/Gems/SupportGemEnergyShieldLeech" enableGlobal2="false" quality="20" skillId="SupportEnergyShieldLeech" enabled="true" nameSpec="Energy Leech"/>
		</Skill>
		<Skill source="Item:7:Shaper&apos;s Touch, Crusader Gloves" mainActiveSkillCalcs="1" label="" enabled="true" slot="Gloves" mainActiveSkill="1">
			<Gem level="12" enableGlobal1="true" gemId="Metadata/Items/Gems/SkillGemElementalWeakness" enableGlobal2="false" quality="0" skillId="ElementalWeakness" enabled="true" nameSpec="Elemental Weakness"/>
		</Skill>
	</Skills>
	<Tree activeSpec="1">
		<Spec>
			<URL>
				https://www.pathofexile.com/passive-skill-tree/AAAABAMBABzcenBbrypNFHVR-48akApV4Czp-wnquuOEKU-nK-GIwGaC5FhauJPfmITFoS8bJQ5IS661SHzlrTORB0J67BjYJL6Kf8YZtIKbDXySdFgH9toy0Y9GuNA_J249YEPTfhvIJJ3G93gvKPoZ1-vukyexBXC77DjNFoaz73rfisSi0NBGcaTCGGqnCGwLwcVtbOkCFX5KyDD4GYr2o4MJtQS-gLv8VkiMdiy_8Yq0DBUgj_oaj3vDbRktg5ARhXsfGFMOZlT-szY9d-UWvySL2VsRluQiz92Krx2qEVB88FfJIvQPqzBbX2pqG13ynjxFR5cG3Q2btWJa2jpSKQDuytPDOpuhvqc=
			</URL>
			<Sockets>
				<Socket nodeId="7960" itemId="20"/>
				<Socket nodeId="61834" itemId="24"/>
				<Socket nodeId="28475" itemId="0"/>
				<Socket nodeId="26196" itemId="19"/>
				<Socket nodeId="36634" itemId="21"/>
				<Socket nodeId="33989" itemId="23"/>
				<Socket nodeId="21984" itemId="18"/>
				<Socket nodeId="46882" itemId="0"/>
				<Socket nodeId="61419" itemId="0"/>
				<Socket nodeId="41263" itemId="17"/>
				<Socket nodeId="60735" itemId="0"/>
				<Socket nodeId="55190" itemId="0"/>
				<Socket nodeId="48768" itemId="16"/>
				<Socket nodeId="54127" itemId="0"/>
				<Socket nodeId="31683" itemId="25"/>
				<Socket nodeId="34483" itemId="22"/>
				<Socket nodeId="26725" itemId="0"/>
				<Socket nodeId="33631" itemId="0"/>
				<Socket nodeId="6230" itemId="0"/>
				<Socket nodeId="2491" itemId="0"/>
				<Socket nodeId="32763" itemId="0"/>
			</Sockets>
		</Spec>
	</Tree>
	<Notes>
		
	</Notes>
	<TreeView searchStr="" zoomY="73.726851851852" showHeatMap="false" zoomLevel="3" showStatDifferences="true" zoomX="-95.212962962963"/>
	<Items activeItemSet="1" useSecondWeaponSet="false">
		<Item id="1">
			Rarity: RARE
Gale Slippers
Sorcerer Boots
Unique ID: 579ea73734e473167368b027f7cf39a6605d0991035a7e13ebdb722318e32ae9
Item Level: 84
Quality: 47
Sockets: B-B-B-G
LevelReq: 72
Implicits: 2
+30 to maximum Energy Shield
{crafted}80% chance to Avoid being Stunned if you&apos;ve Killed Recently
+32 to Intelligence
+38 to maximum Energy Shield
175% increased Energy Shield
16% increased Stun and Block Recovery
{crafted}+21 to Strength
{crafted}+18% to Quality
		</Item>
		<Item id="2">
			Rarity: RARE
Blight Gorget
Paua Amulet
Unique ID: 21d4ed65ee854ac79cd36d0a897228acdfee1700baff42fb98dd3fed5e9e31b8
Item Level: 84
Quality: 0
LevelReq: 59
Implicits: 2
15% increased Intelligence
1% increased Damage per 15 Intelligence
+49 to Intelligence
Adds 3 to 34 Lightning Damage to Attacks
19% increased maximum Energy Shield
16% increased Energy Shield from Body Armour
{crafted}14% increased Projectile Speed
{crafted}13% increased Projectile Damage
{crafted}+14 to Strength and Intelligence
		</Item>
		<Item id="3">
			Rarity: RARE
Wrath Grasp
Ruby Ring
Unique ID: 67568c68c50fe75dbc79d4a0d5d64e29cbf97cb80c27170befbc4c263d5b59f9
Item Level: 83
Quality: 0
LevelReq: 52
Implicits: 1
6% increased Intelligence
+39 to Strength
+35 to Intelligence
Adds 3 to 7 Cold Damage to Attacks
31% increased Elemental Damage with Attack Skills
{crafted}+12% to all Elemental Resistances
		</Item>
		<Item id="4">
			Rarity: UNIQUE
Atziri&apos;s Reflection
Golden Buckler
Unique ID: 1b0799b777a637b3a9d19f639bc55149fd6de9107c095e63816368e59d626006
Item Level: 70
Quality: 28
Sockets: B-G-G
LevelReq: 54
Implicits: 1
6% increased Movement Speed
+57 to Intelligence
192% increased Evasion Rating
+193 to maximum Energy Shield
+30% to all Elemental Resistances
Curse Reflection
Unaffected by Curses
20% increased Effect of your Curses
		</Item>
		<Item id="5">
			Rarity: UNIQUE
Hand of Wisdom and Action
Imperial Claw
Unique ID: 1228514cdafd7806e474402fe0e114834db16b162de5c72e9537f724247a644c
Item Level: 72
Quality: 20
Sockets: R-G-G
LevelReq: 68
Implicits: 1
6% increased Attack Speed
10% increased Dexterity
12% increased Intelligence
Adds 1 to 10 Lightning Damage to Attacks with this Weapon per 10 Intelligence
1% increased Attack Speed per 25 Dexterity
30% increased Elemental Damage with Attack Skills
Corrupted
		</Item>
		<Item id="6">
			Rarity: RARE
Kraken Star
Hubris Circlet
Unique ID: 99689d9e045923e875900a96b54d1481dbf60fddfcbce1fba14a6450ffd95def
Item Level: 83
Quality: 48
Sockets: W-B-B-B
LevelReq: 72
Implicits: 3
+30 to maximum Energy Shield
16% increased Energy Shield
{crafted}Molten Strike fires 2 additional Projectiles
+49 to maximum Energy Shield
159% increased Energy Shield
10% increased Stun and Block Recovery
{crafted}+25 to Intelligence
{crafted}+18% to Quality
		</Item>
		<Item id="7">
			Rarity: UNIQUE
Shaper&apos;s Touch
Crusader Gloves
Unique ID: 60ba63384a92319622b46fc85dcc6c74c05f3c5339f0f4cc2a52775b09aaa3e7
Shaper Item
Item Level: 86
Quality: 20
Sockets: G-R-R-R
LevelReq: 66
Implicits: 1
Curse Enemies with Level 12 Elemental Weakness on Hit
88% increased Armour and Energy Shield
+4 Accuracy Rating per 2 Intelligence
+1 Life per 4 Dexterity
+2 Mana per 4 Strength
2% increased Energy Shield per 10 Strength
2% increased Evasion Rating per 10 Intelligence
2% increased Melee Physical Damage per 10 Dexterity
Corrupted
		</Item>
		<Item id="8">
			Rarity: RARE
Ghoul Shroud
Vaal Regalia
Unique ID: 2772eaa3e3e8de68a4f9153fb4652f6494183318db3659baf2d5911e9a6785bd
Shaper Item
Item Level: 86
Quality: 46
Sockets: R-R-R-B-R-B
LevelReq: 72
Implicits: 0
100% increased Energy Shield
12% increased Intelligence
{crafted}Can have multiple Crafted Modifiers
{crafted}+25 to Intelligence
{crafted}+69 to maximum Energy Shield
{crafted}You can apply an additional Curse
{crafted}+16% to Quality
		</Item>
		<Item id="9">
			Rarity: RARE
Damnation Lock
Crystal Belt
Unique ID: e16e042a7620865b9d7674aa2cfd713c2d64cdd755c4a07d42fcc8814fe54f35
Elder Item
Item Level: 83
LevelReq: 79
Implicits: 1
+79 to maximum Energy Shield
+48 to Intelligence
+99 to maximum Life
30% increased Stun Duration on Enemies
12% increased Attributes
{crafted}30% increased Elemental Damage with Attack Skills
		</Item>
		<Item id="10">
			Rarity: RARE
Spirit Grasp
Two-Stone Ring
Unique ID: 9033f8f6c2562f5a682dceee03f67b24e3f3047e07357bd73ab4eee841170a56
Item Level: 83
Quality: 0
LevelReq: 65
Implicits: 1
6% increased Intelligence
+16 to all Attributes
+53 to Strength
+43 to Intelligence
+134 to Evasion Rating
+60 to maximum Mana
{crafted}21% increased Elemental Damage with Attack Skills
		</Item>
		<Item id="11">
			Rarity: MAGIC
Chemist&apos;s Silver Flask of Warding
Unique ID: f1395b67d9b9200d80b49c624a3ff1f9047df34cfeb1920f88a5474d3fcf7c01
Item Level: 72
Quality: 0
LevelReq: 22
Implicits: 0
24% reduced Charges used
Immune to Curses during Flask effect
Removes Curses on use
		</Item>
		<Item id="12">
			Rarity: MAGIC
Chemist&apos;s Topaz Flask of Grounding
Unique ID: db0cc2f5165e28204c87548ef1908a519ac73449e366781e9f1b58577681e8de
Item Level: 53
Quality: 20
LevelReq: 18
Implicits: 0
23% reduced Charges used
Immunity to Shock during Flask effect
Removes Shock on use
		</Item>
		<Item id="13">
			Rarity: MAGIC
Chemist&apos;s Jade Flask of Heat
Unique ID: e3a3d6864c85105d7f112223a46dd3cc9676e7dab951c4b79d54c48e01406ded
Item Level: 70
Quality: 20
LevelReq: 27
Implicits: 0
25% reduced Charges used
Immunity to Freeze and Chill during Flask effect
Removes Freeze and Chill on use
		</Item>
		<Item id="14">
			Rarity: MAGIC
Alchemist&apos;s Quicksilver Flask of Adrenaline
Unique ID: 3384925681cad2886c3f40a13494196cfe3c6d3c9efa9186b78db0a64619aca2
Item Level: 74
Quality: 20
LevelReq: 16
Implicits: 0
29% increased Movement Speed during Flask effect
25% increased effect
33% reduced Duration
		</Item>
		<Item id="15">
			Rarity: UNIQUE
Dying Sun
Ruby Flask
Unique ID: 4745bc62a5959379c06c1c304e0cad59e4f4d8e1f055a29694b508e8531dd5c3
Item Level: 86
Quality: 20
LevelReq: 18
Implicits: 0
8% reduced Charges used
Skills fire 2 additional Projectiles during Flask Effect
23% increased Area of Effect during Flask Effect
		</Item>
		<Item id="16">
			Rarity: UNIQUE
Emperor&apos;s Mastery
Prismatic Jewel
Unique ID: 49592c94c75101cc8ff8ab2894a6ce98c06df34d911ac7c8174dc726142f674d
Item Level: 100
Implicits: 0
4% increased maximum Life
3% increased Character Size
5% increased Global Defences
7% increased Attributes
		</Item>
		<Item id="17">
			Rarity: RARE
Brood Solace
Cobalt Jewel
Unique ID: fb1f47edcfc91d94bc12d775f61ad2b4cefd89137692bf8ee095f596cba40690
Item Level: 81
Implicits: 0
6% increased Attack Speed while holding a Shield
8% increased maximum Energy Shield
+10% to all Elemental Resistances
+9 to Strength and Intelligence
		</Item>
		<Item id="18">
			Rarity: RARE
Dragon Needle
Viridian Jewel
Unique ID: df53ce9a1900ae01a79ea4b59ce5ee01fb2f12c0105d5fa80c0ba43e55797240
Item Level: 80
Implicits: 0
4% increased Attack Speed
4% increased Attack Speed with One Handed Melee Weapons
8% increased Attack Speed with Claws
+10% to all Elemental Resistances
		</Item>
		<Item id="19">
			Rarity: UNIQUE
Wildfire
Crimson Jewel
Unique ID: cddf4c3a4e5783b0915311ae07a936156413578e2dc0c103300af13dd060ebe0
Item Level: 77
Radius: Medium
Implicits: 1
Corrupted Blood cannot be inflicted on you
10% increased Fire Damage
With at least 40 Strength in Radius, Molten Strike fires 2 additional Projectiles
With at least 40 Strength in Radius, Molten Strike has 25% increased Area of Effect
Corrupted
		</Item>
		<Item id="20">
			Rarity: RARE
Vivid Impaler
Viridian Jewel
Unique ID: 869dc6f2637b5317a9b4e454367fff952c336c7c948fb800c8ece158a860ff28
Item Level: 57
Implicits: 0
8% increased Damage
6% increased Attack Speed with One Handed Melee Weapons
8% increased Attack Speed with Claws
+10% to all Elemental Resistances
		</Item>
		<Item id="21">
			Rarity: UNIQUE
Watcher&apos;s Eye
Prismatic Jewel
Unique ID: a8fb6d130344d6206b5528b17f61adc393123d3e31ec537e50a337c10b621991
Item Level: 86
Implicits: 0
5% increased maximum Energy Shield
6% increased maximum Life
6% increased maximum Mana
+30 Energy Shield gained for each Enemy Hit while affected by Discipline
Gain Arcane Surge for 4 seconds when you create Consecrated Ground while affected by Zealotry
Gain 18% of Maximum Mana as Extra Maximum Energy Shield while affected by Clarity
		</Item>
		<Item id="22">
			Rarity: UNIQUE
Fertile Mind
Cobalt Jewel
Unique ID: 3e1fb3ae9c71fc36d2f605dff25a74845b68743b0b8e1f888709ba8b44a9a3a4
Item Level: 80
Radius: Large
Implicits: 1
4% increased Damage
+24 to Intelligence
Dexterity from Passives in Radius is Transformed to Intelligence
Corrupted
		</Item>
		<Item id="23">
			Rarity: UNIQUE
Fertile Mind
Cobalt Jewel
Unique ID: 485a3deeb055e5ecc7a28265501ae9485aa7838354de8713e1d8a06f5fba0c4d
Item Level: 71
Radius: Large
Implicits: 1
9% increased Global Critical Strike Chance
+24 to Intelligence
Dexterity from Passives in Radius is Transformed to Intelligence
Corrupted
		</Item>
		<Item id="24">
			Rarity: UNIQUE
Fertile Mind
Cobalt Jewel
Unique ID: e1199859e671dd98c833f447d354af2c9ea1224d10809570762e6e2cfaaefb9e
Item Level: 78
Radius: Large
Implicits: 1
5% increased Damage
+21 to Intelligence
Dexterity from Passives in Radius is Transformed to Intelligence
Corrupted
		</Item>
		<Item id="25">
			Rarity: UNIQUE
The Red Nightmare
Crimson Jewel
Unique ID: b58b2ce71b1503f5eb00acdd201e496e0b37d46ce0b25d9ab7a083c8b7741b85
Item Level: 85
Radius: Large
Implicits: 0
Gain 5% of Fire Damage as Extra Chaos Damage
Passives granting Fire Resistance or all Elemental Resistances in Radius
also grant Chance to Block Attack Damage at 35% of its value
Passives granting Fire Resistance or all Elemental Resistances in Radius
also grant an equal chance to gain an Endurance Charge on Kill
		</Item>
		<Slot name="Gloves" itemId="7"/>
		<Slot name="Weapon 1" itemId="5"/>
		<Slot active="true" name="Flask 3" itemId="13"/>
		<Slot name="Amulet" itemId="2"/>
		<Slot active="true" name="Flask 1" itemId="15"/>
		<Slot active="true" name="Flask 5" itemId="14"/>
		<Slot active="true" name="Flask 2" itemId="12"/>
		<Slot name="Weapon 2" itemId="4"/>
		<Slot name="Body Armour" itemId="8"/>
		<Slot active="true" name="Flask 4" itemId="11"/>
		<Slot name="Ring 2" itemId="10"/>
		<Slot name="Boots" itemId="1"/>
		<Slot name="Ring 1" itemId="3"/>
		<Slot name="Helmet" itemId="6"/>
		<Slot name="Belt" itemId="9"/>
		<ItemSet useSecondWeaponSet="false" id="1">
			<Slot name="Gloves" itemId="7"/>
			<Slot name="Weapon 1" itemId="5"/>
			<Slot name="Weapon 2Swap Abyssal Socket 2" itemId="0"/>
			<Slot name="Belt Abyssal Socket 2" itemId="0"/>
			<Slot active="true" name="Flask 3" itemId="13"/>
			<Slot name="Body Armour Abyssal Socket 2" itemId="0"/>
			<Slot name="Amulet" itemId="2"/>
			<Slot active="true" name="Flask 1" itemId="15"/>
			<Slot name="Weapon 2Swap Abyssal Socket 1" itemId="0"/>
			<Slot active="true" name="Flask 5" itemId="14"/>
			<Slot name="Belt Abyssal Socket 1" itemId="0"/>
			<Slot active="true" name="Flask 2" itemId="12"/>
			<Slot name="Helmet Abyssal Socket 2" itemId="0"/>
			<Slot name="Weapon 2 Swap" itemId="0"/>
			<Slot name="Weapon 1 Abyssal Socket 1" itemId="0"/>
			<Slot name="Weapon 2" itemId="4"/>
			<Slot name="Body Armour" itemId="8"/>
			<Slot active="true" name="Flask 4" itemId="11"/>
			<Slot name="Weapon 1 Abyssal Socket 2" itemId="0"/>
			<Slot name="Weapon 2 Abyssal Socket 2" itemId="0"/>
			<Slot name="Weapon 1 Swap" itemId="0"/>
			<Slot name="Ring 2" itemId="10"/>
			<Slot name="Boots Abyssal Socket 2" itemId="0"/>
			<Slot name="Gloves Abyssal Socket 2" itemId="0"/>
			<Slot name="Body Armour Abyssal Socket 1" itemId="0"/>
			<Slot name="Gloves Abyssal Socket 1" itemId="0"/>
			<Slot name="Helmet Abyssal Socket 1" itemId="0"/>
			<Slot name="Weapon 2 Abyssal Socket 1" itemId="0"/>
			<Slot name="Boots" itemId="1"/>
			<Slot name="Weapon 1Swap Abyssal Socket 1" itemId="0"/>
			<Slot name="Ring 1" itemId="3"/>
			<Slot name="Weapon 1Swap Abyssal Socket 2" itemId="0"/>
			<Slot name="Helmet" itemId="6"/>
			<Slot name="Boots Abyssal Socket 1" itemId="0"/>
			<Slot name="Belt" itemId="9"/>
		</ItemSet>
	</Items>
	<Config>
		<Input name="conditionFullLife" boolean="true"/>
		<Input name="enemyIsBoss" string="SHAPER"/>
		<Input name="multiplierKilledRecently" number="30"/>
		<Input name="projectileDistance" number="10"/>
		<Input name="brandAttachedToEnemy" boolean="true"/>
		<Input name="useEnduranceCharges" boolean="true"/>
		<Input name="conditionHaveEnergyShield" boolean="true"/>
		<Input name="conditionFullEnergyShield" boolean="true"/>
		<Input name="conditionEnemyIgnited" boolean="true"/>
		<Input name="buffFortify" boolean="true"/>
		<Input name="conditionEnemyBleeding" boolean="true"/>
		<Input name="conditionEnemyChilled" boolean="true"/>
	</Config>
</PathOfBuilding>
